odoo/addons/donation_direct_debit/README.rst
odoo/addons/donation_direct_debit/__init__.py
odoo/addons/donation_direct_debit/__manifest__.py
odoo/addons/donation_direct_debit/demo/donation_demo.xml
odoo/addons/donation_direct_debit/i18n/de.po
odoo/addons/donation_direct_debit/i18n/donation_direct_debit.pot
odoo/addons/donation_direct_debit/i18n/es.po
odoo/addons/donation_direct_debit/i18n/fr.po
odoo/addons/donation_direct_debit/i18n/it.po
odoo/addons/donation_direct_debit/models/__init__.py
odoo/addons/donation_direct_debit/models/donation.py
odoo/addons/donation_direct_debit/models/res_company.py
odoo/addons/donation_direct_debit/readme/CONFIGURE.rst
odoo/addons/donation_direct_debit/readme/CONTRIBUTORS.rst
odoo/addons/donation_direct_debit/readme/DESCRIPTION.rst
odoo/addons/donation_direct_debit/readme/USAGE.rst
odoo/addons/donation_direct_debit/static/description/icon.png
odoo/addons/donation_direct_debit/static/description/index.html
odoo/addons/donation_direct_debit/tests/__init__.py
odoo/addons/donation_direct_debit/tests/test_direct_debit.py
odoo/addons/donation_direct_debit/views/donation.xml
odoo/addons/donation_direct_debit/wizards/__init__.py
odoo/addons/donation_direct_debit/wizards/res_config_settings.py
odoo/addons/donation_direct_debit/wizards/res_config_settings.xml
odoo_addon_donation_direct_debit-16.0.2.0.0.2.dist-info/METADATA
odoo_addon_donation_direct_debit-16.0.2.0.0.2.dist-info/WHEEL
odoo_addon_donation_direct_debit-16.0.2.0.0.2.dist-info/top_level.txt
odoo_addon_donation_direct_debit-16.0.2.0.0.2.dist-info/RECORD
