Metadata-Version: 2.1
Name: odoo-addon-donation-direct-debit
Version: 16.0.2.0.0.2
Summary: Auto-generate direct debit order on donation validation
Home-page: https://github.com/OCA/donation
Author: Akretion, Odoo Community Association (OCA)
Author-email: support@odoo-community.org
License: AGPL-3
Platform: UNKNOWN
Classifier: Programming Language :: Python
Classifier: Framework :: Odoo
Classifier: Framework :: Odoo :: 16.0
Classifier: License :: OSI Approved :: GNU Affero General Public License v3
Requires-Python: >=3.10
Requires-Dist: odoo-addon-account-banking-sepa-direct-debit <16.1dev,>=16.0dev
Requires-Dist: odoo-addon-donation <16.1dev,>=16.0dev
Requires-Dist: odoo <16.1dev,>=16.0a
